SuperPyLib/Get.py
SuperPyLib/Mesh.py
SuperPyLib/Output.py
SuperPyLib/PlotUtils.py
SuperPyLib/__init__.py
SuperPyLib/Geometry/Boolean.py
SuperPyLib/Geometry/Geometry.py
SuperPyLib/Geometry/__init__.py
SuperPyLib/Solvers/Electrostatic.py
SuperPyLib/Solvers/Magnetostatic.py
SuperPyLib/Solvers/Solve.py
SuperPyLib/Solvers/Solver.py
SuperPyLib/Solvers/Structural.py
SuperPyLib/Solvers/Thermostatic.py
SuperPyLib/Solvers/__init__.py
superpylib-0.0.9.dist-info/METADATA
superpylib-0.0.9.dist-info/WHEEL
superpylib-0.0.9.dist-info/licenses/LICENSE
superpylib-0.0.9.dist-info/RECORD
