Metadata-Version: 2.1
Name: SuperPyLib
Version: 0.0.9
Summary: Package for calculating 2-D integral and finite element numerical solutions for Poisson equation with non-overlapping shapes in the presence of Superconducting materials. Updated Get module with straight forward explicit expression for Electric field.
Project-URL: Homepage, https://github.com/nithingoona/SuperPyLib
Project-URL: Bug Tracker, https://github.com/nithingoona/SuperPyLib/issues
Author-email: Nithin Goona <nithin.goona@gmail.com>
License-File: LICENSE
Classifier: License :: OSI Approved :: MIT License
Classifier: Operating System :: OS Independent
Classifier: Programming Language :: Python :: 3
Requires-Python: >=3.8
